np_zro-0.1.0.post4.dist-info/METADATA
np_zro-0.1.0.post4.dist-info/WHEEL
np_zro/__init__.py
np_zro/zro.py
np_zro-0.1.0.post4.dist-info/RECORD
