Metadata-Version: 2.1
Name: np-zro
Version: 0.1.0.post4
Summary: Just the `zro.Proxy` class extracted from `mpeconfig`, with `zmq` as a dependency.
Author-Email: derricw <derricw@alleninstitute.org>, rossh <rossh@alleninstitute.org>
Maintainer-Email: bjhardcastle <ben.hardcastle@alleninstitute.org>
Classifier: Programming Language :: Python :: 3
Classifier: Programming Language :: Python :: 3.7
Classifier: Programming Language :: Python :: 3.8
Classifier: Programming Language :: Python :: 3.9
Classifier: Programming Language :: Python :: 3.10
Classifier: Programming Language :: Python :: 3.11
Project-URL: Repository, https://github.com/AllenInstitute/np_zro
Project-URL: Bug tracker, https://github.com/AllenInstitute/np_zro/issues
Requires-Python: >=3.7
Requires-Dist: zmq>=0.0.0
Requires-Dist: typing-extensions>=4.5.0
